[
     {
          "dialogue_id": 136,
          "services": [
               "Calendar_1"
          ],
          "turns": [
               {
                    "frames": [
                         {
                              "actions": [
                                   {
                                        "act": "INFORM_INTENT",
                                        "canonical_values": [
                                             "AddEvent"
                                        ],
                                        "slot": "intent",
                                        "values": [
                                             "AddEvent"
                                        ]
                                   }
                              ],
                              "service": "Calendar_1",
                              "slots": [],
                              "state": {
                                   "active_intent": "AddEvent",
                                   "requested_slots": [],
                                   "slot_values": {}
                              }
                         }
                    ],
                    "speaker": "USER",
                    "utterance": "請幫我在行事曆添加一個活動"
               },
               {
                    "frames": [
                         {
                              "actions": [
                                   {
                                        "act": "REQUEST",
                                        "canonical_values": [],
                                        "slot": "event_name",
                                        "values": []
                                   },
                                   {
                                        "act": "REQUEST",
                                        "canonical_values": [],
                                        "slot": "event_content",
                                        "values": []
                                   }
                              ],
                              "service": "Calendar_1",
                              "slots": [],
                              "service_results": []
                         }
                    ],
                    "speaker": "SYSTEM",
                    "utterance": "那這個活動叫甚麼呢？，這個活動有任何內容註記嗎？"
               },
               {
                    "frames": [
                         {
                              "actions": [
                                   {
                                        "act": "INFORM",
                                        "canonical_values": [
                                             "[取消辦理]年第8屆鹿野馬拉松"
                                        ],
                                        "slot": "event_name",
                                        "values": [
                                             "[取消辦理]年第8屆鹿野馬拉松"
                                        ]
                                   },
                                   {
                                        "act": "INFORM",
                                        "canonical_values": [
                                             "鹿野馬拉松將帶領各位跑友，進入風景佳空氣好的花東縱谷"
                                        ],
                                        "slot": "event_content",
                                        "values": [
                                             "鹿野馬拉松將帶領各位跑友，進入風景佳空氣好的花東縱谷"
                                        ]
                                   }
                              ],
                              "service": "Calendar_1",
                              "slots": [
                                   {
                                        "exclusive_end": 20,
                                        "slot": "event_name",
                                        "start": 5
                                   },
                                   {
                                        "exclusive_end": 52,
                                        "slot": "event_content",
                                        "start": 26
                                   }
                              ],
                              "state": {
                                   "active_intent": "AddEvent",
                                   "requested_slots": [],
                                   "slot_values": {
                                        "event_name": [
                                             "[取消辦理]年第8屆鹿野馬拉松"
                                        ],
                                        "event_content": [
                                             "鹿野馬拉松將帶領各位跑友，進入風景佳空氣好的花東縱谷"
                                        ]
                                   }
                              }
                         }
                    ],
                    "speaker": "USER",
                    "utterance": "活動名稱為[取消辦理]年第8屆鹿野馬拉松，活動內容為鹿野馬拉松將帶領各位跑友，進入風景佳空氣好的花東縱谷"
               },
               {
                    "frames": [
                         {
                              "actions": [
                                   {
                                        "act": "REQUEST",
                                        "canonical_values": [],
                                        "slot": "event_time",
                                        "values": []
                                   }
                              ],
                              "service": "Calendar_1",
                              "slots": [],
                              "service_results": []
                         }
                    ],
                    "speaker": "SYSTEM",
                    "utterance": "這個活動在幾點開始呢？"
               },
               {
                    "frames": [
                         {
                              "actions": [
                                   {
                                        "act": "INFORM",
                                        "canonical_values": [
                                             "12:13"
                                        ],
                                        "slot": "event_time",
                                        "values": [
                                             "12點13分"
                                        ]
                                   }
                              ],
                              "service": "Calendar_1",
                              "slots": [
                                   {
                                        "exclusive_end": 9,
                                        "slot": "event_time",
                                        "start": 3
                                   }
                              ],
                              "state": {
                                   "active_intent": "AddEvent",
                                   "requested_slots": [],
                                   "slot_values": {
                                        "event_name": [
                                             "[取消辦理]年第8屆鹿野馬拉松"
                                        ],
                                        "event_content": [
                                             "鹿野馬拉松將帶領各位跑友，進入風景佳空氣好的花東縱谷"
                                        ],
                                        "event_time": [
                                             "12點13分"
                                        ]
                                   }
                              }
                         }
                    ],
                    "speaker": "USER",
                    "utterance": "時間為12點13分"
               },
               {
                    "frames": [
                         {
                              "actions": [
                                   {
                                        "act": "REQUEST",
                                        "canonical_values": [],
                                        "slot": "event_date",
                                        "values": []
                                   }
                              ],
                              "service": "Calendar_1",
                              "slots": [],
                              "service_results": []
                         }
                    ],
                    "speaker": "SYSTEM",
                    "utterance": "這個活動辦在幾月幾號呢？"
               },
               {
                    "frames": [
                         {
                              "actions": [
                                   {
                                        "act": "INFORM",
                                        "canonical_values": [
                                             "2022/3/26"
                                        ],
                                        "slot": "event_date",
                                        "values": [
                                             "2022年3月26號"
                                        ]
                                   }
                              ],
                              "service": "Calendar_1",
                              "slots": [
                                   {
                                        "exclusive_end": 13,
                                        "slot": "event_date",
                                        "start": 3
                                   }
                              ],
                              "state": {
                                   "active_intent": "AddEvent",
                                   "requested_slots": [],
                                   "slot_values": {
                                        "event_name": [
                                             "[取消辦理]年第8屆鹿野馬拉松"
                                        ],
                                        "event_content": [
                                             "鹿野馬拉松將帶領各位跑友，進入風景佳空氣好的花東縱谷"
                                        ],
                                        "event_time": [
                                             "12點13分"
                                        ],
                                        "event_date": [
                                             "2022年3月26號"
                                        ]
                                   }
                              }
                         }
                    ],
                    "speaker": "USER",
                    "utterance": "活動在2022年3月26號"
               },
               {
                    "frames": [
                         {
                              "actions": [
                                   {
                                        "act": "CONFIRM",
                                        "canonical_values": [
                                             "[取消辦理]年第8屆鹿野馬拉松"
                                        ],
                                        "slot": "event_name",
                                        "values": [
                                             "[取消辦理]年第8屆鹿野馬拉松"
                                        ]
                                   },
                                   {
                                        "act": "CONFIRM",
                                        "canonical_values": [
                                             "鹿野馬拉松將帶領各位跑友，進入風景佳空氣好的花東縱谷"
                                        ],
                                        "slot": "event_content",
                                        "values": [
                                             "鹿野馬拉松將帶領各位跑友，進入風景佳空氣好的花東縱谷"
                                        ]
                                   },
                                   {
                                        "act": "CONFIRM",
                                        "canonical_values": [
                                             "12點13分"
                                        ],
                                        "slot": "event_time",
                                        "values": [
                                             "12點13分"
                                        ]
                                   },
                                   {
                                        "act": "CONFIRM",
                                        "canonical_values": [
                                             "2022年3月26號"
                                        ],
                                        "slot": "event_date",
                                        "values": [
                                             "2022年3月26號"
                                        ]
                                   }
                              ],
                              "service": "Calendar_1",
                              "slots": [],
                              "service_results": []
                         }
                    ],
                    "speaker": "SYSTEM",
                    "utterance": "確認要建立名叫[取消辦理]年第8屆鹿野馬拉松的活動嗎？"
               },
               {
                    "frames": [
                         {
                              "actions": [
                                   {
                                        "act": "AFFIRM",
                                        "canonical_values": [],
                                        "slot": "",
                                        "values": []
                                   }
                              ],
                              "service": "Calendar_1",
                              "slots": [],
                              "state": {
                                   "active_intent": "AddEvent",
                                   "requested_slots": [],
                                   "slot_values": {
                                        "event_name": [
                                             "[取消辦理]年第8屆鹿野馬拉松"
                                        ],
                                        "event_content": [
                                             "鹿野馬拉松將帶領各位跑友，進入風景佳空氣好的花東縱谷"
                                        ],
                                        "event_time": [
                                             "12點13分"
                                        ],
                                        "event_date": [
                                             "2022年3月26號"
                                        ]
                                   }
                              }
                         }
                    ],
                    "speaker": "USER",
                    "utterance": "我對以上資訊沒問題"
               },
               {
                    "frames": [
                         {
                              "actions": [
                                   {
                                        "act": "NOTIFY_SUCCESS",
                                        "canonical_values": [],
                                        "slot": "",
                                        "values": []
                                   }
                              ],
                              "service": "Calendar_1",
                              "slots": [],
                              "service_call": {
                                   "method": "AddEvent",
                                   "parameters": {
                                        "event_name": "[取消辦理]年第8屆鹿野馬拉松",
                                        "event_content": "鹿野馬拉松將帶領各位跑友，進入風景佳空氣好的花東縱谷",
                                        "event_time": "12點13分",
                                        "event_date": "2022年3月26號"
                                   }
                              },
                              "service_results": []
                         }
                    ],
                    "speaker": "SYSTEM",
                    "utterance": "多虧有您的配合，活動已添加至行事曆"
               },
               {
                    "frames": [
                         {
                              "actions": [
                                   {
                                        "act": "GOODBYE",
                                        "canonical_values": [],
                                        "slot": "",
                                        "values": []
                                   }
                              ],
                              "service": "Calendar_1",
                              "slots": [],
                              "state": {
                                   "active_intent": "AddEvent",
                                   "requested_slots": [],
                                   "slot_values": {
                                        "event_name": [
                                             "[取消辦理]年第8屆鹿野馬拉松"
                                        ],
                                        "event_content": [
                                             "鹿野馬拉松將帶領各位跑友，進入風景佳空氣好的花東縱谷"
                                        ],
                                        "event_time": [
                                             "12點13分"
                                        ],
                                        "event_date": [
                                             "2022年3月26號"
                                        ]
                                   }
                              }
                         }
                    ],
                    "speaker": "USER",
                    "utterance": "沒有了！再見！"
               },
               {
                    "frames": [
                         {
                              "actions": [
                                   {
                                        "act": "GOODBYE",
                                        "canonical_values": [],
                                        "slot": "",
                                        "values": []
                                   }
                              ],
                              "service": "Calendar_1",
                              "slots": [],
                              "service_call": {
                                   "method": "AddEvent",
                                   "parameters": {
                                        "event_name": "[取消辦理]年第8屆鹿野馬拉松",
                                        "event_content": "鹿野馬拉松將帶領各位跑友，進入風景佳空氣好的花東縱谷",
                                        "event_time": "12點13分",
                                        "event_date": "2022年3月26號"
                                   }
                              },
                              "service_results": []
                         }
                    ],
                    "speaker": "SYSTEM",
                    "utterance": "再見"
               }
          ]
     }
]