[
     {
          "dialogue_id": 559,
          "services": [
               "Messaging_1",
               "Calendar_1"
          ],
          "turns": [
               {
                    "frames": [
                         {
                              "actions": [
                                   {
                                        "act": "INFORM_INTENT",
                                        "canonical_values": [
                                             "SendMessage"
                                        ],
                                        "slot": "intent",
                                        "values": [
                                             "SendMessage"
                                        ]
                                   }
                              ],
                              "service": "Messaging_1",
                              "slots": [],
                              "state": {
                                   "active_intent": "SendMessage",
                                   "requested_slots": [],
                                   "slot_values": {}
                              }
                         }
                    ],
                    "speaker": "USER",
                    "utterance": "我想要寄則訊息，可以請你幫忙嗎？"
               },
               {
                    "frames": [
                         {
                              "actions": [
                                   {
                                        "act": "REQUEST",
                                        "canonical_values": [],
                                        "slot": "message",
                                        "values": []
                                   }
                              ],
                              "service": "Messaging_1",
                              "slots": [],
                              "service_results": []
                         }
                    ],
                    "speaker": "SYSTEM",
                    "utterance": "我想知道訊息內容"
               },
               {
                    "frames": [
                         {
                              "actions": [
                                   {
                                        "act": "INFORM",
                                        "canonical_values": [
                                             "我以為ai工作 僧多粥少"
                                        ],
                                        "slot": "message",
                                        "values": [
                                             "我以為ai工作 僧多粥少"
                                        ]
                                   }
                              ],
                              "service": "Messaging_1",
                              "slots": [
                                   {
                                        "exclusive_end": 15,
                                        "slot": "message",
                                        "start": 3
                                   }
                              ],
                              "state": {
                                   "active_intent": "SendMessage",
                                   "requested_slots": [],
                                   "slot_values": {
                                        "message": [
                                             "我以為ai工作 僧多粥少"
                                        ]
                                   }
                              }
                         }
                    ],
                    "speaker": "USER",
                    "utterance": "跟他說我以為ai工作 僧多粥少"
               },
               {
                    "frames": [
                         {
                              "actions": [
                                   {
                                        "act": "REQUEST",
                                        "canonical_values": [],
                                        "slot": "contact_name",
                                        "values": []
                                   },
                                   {
                                        "act": "REQUEST",
                                        "canonical_values": [],
                                        "slot": "group_name",
                                        "values": []
                                   }
                              ],
                              "service": "Messaging_1",
                              "slots": [],
                              "service_results": []
                         }
                    ],
                    "speaker": "SYSTEM",
                    "utterance": "你知道群組名稱嗎？，我想知道這則訊息是誰寄的？"
               },
               {
                    "frames": [
                         {
                              "actions": [
                                   {
                                        "act": "INFORM",
                                        "canonical_values": [
                                             "Jerome"
                                        ],
                                        "slot": "contact_name",
                                        "values": [
                                             "Jerome"
                                        ]
                                   },
                                   {
                                        "act": "INFORM",
                                        "canonical_values": [
                                             "AI 人工智慧"
                                        ],
                                        "slot": "group_name",
                                        "values": [
                                             "AI 人工智慧"
                                        ]
                                   }
                              ],
                              "service": "Messaging_1",
                              "slots": [
                                   {
                                        "exclusive_end": 27,
                                        "slot": "contact_name",
                                        "start": 21
                                   },
                                   {
                                        "exclusive_end": 11,
                                        "slot": "group_name",
                                        "start": 4
                                   }
                              ],
                              "state": {
                                   "active_intent": "SendMessage",
                                   "requested_slots": [],
                                   "slot_values": {
                                        "message": [
                                             "我以為ai工作 僧多粥少"
                                        ],
                                        "contact_name": [
                                             "Jerome"
                                        ],
                                        "group_name": [
                                             "AI 人工智慧"
                                        ]
                                   }
                              }
                         }
                    ],
                    "speaker": "USER",
                    "utterance": "應該是在AI 人工智慧群組中的訊息，用戶為Jerome"
               },
               {
                    "frames": [
                         {
                              "actions": [
                                   {
                                        "act": "CONFIRM",
                                        "canonical_values": [
                                             "我以為ai工作 僧多粥少"
                                        ],
                                        "slot": "message",
                                        "values": [
                                             "我以為ai工作 僧多粥少"
                                        ]
                                   },
                                   {
                                        "act": "CONFIRM",
                                        "canonical_values": [
                                             "Jerome"
                                        ],
                                        "slot": "contact_name",
                                        "values": [
                                             "Jerome"
                                        ]
                                   },
                                   {
                                        "act": "CONFIRM",
                                        "canonical_values": [
                                             "AI 人工智慧"
                                        ],
                                        "slot": "group_name",
                                        "values": [
                                             "AI 人工智慧"
                                        ]
                                   }
                              ],
                              "service": "Messaging_1",
                              "slots": [
                                   {
                                        "exclusive_end": 19,
                                        "slot": "message",
                                        "start": 7
                                   },
                                   {
                                        "exclusive_end": 54,
                                        "slot": "contact_name",
                                        "start": 48
                                   },
                                   {
                                        "exclusive_end": 37,
                                        "slot": "group_name",
                                        "start": 30
                                   }
                              ],
                              "service_results": []
                         }
                    ],
                    "speaker": "SYSTEM",
                    "utterance": "確認要傳送訊息我以為ai工作 僧多粥少嗎？，確認要傳送訊息到AI 人工智慧嗎？，確認要傳送訊息給Jerome嗎？"
               },
               {
                    "frames": [
                         {
                              "actions": [
                                   {
                                        "act": "AFFIRM",
                                        "canonical_values": [],
                                        "slot": "",
                                        "values": []
                                   }
                              ],
                              "service": "Messaging_1",
                              "slots": [],
                              "state": {
                                   "active_intent": "SendMessage",
                                   "requested_slots": [],
                                   "slot_values": {
                                        "message": [
                                             "我以為ai工作 僧多粥少"
                                        ],
                                        "contact_name": [
                                             "Jerome"
                                        ],
                                        "group_name": [
                                             "AI 人工智慧"
                                        ]
                                   }
                              }
                         }
                    ],
                    "speaker": "USER",
                    "utterance": "我對以上資訊沒問題"
               },
               {
                    "frames": [
                         {
                              "actions": [
                                   {
                                        "act": "NOTIFY_SUCCESS",
                                        "canonical_values": [],
                                        "slot": "",
                                        "values": []
                                   }
                              ],
                              "service": "Messaging_1",
                              "slots": [],
                              "service_call": {
                                   "method": "SendMessage",
                                   "parameters": {
                                        "message": "我以為ai工作 僧多粥少",
                                        "contact_name": "Jerome",
                                        "group_name": "AI 人工智慧"
                                   }
                              },
                              "service_results": []
                         }
                    ],
                    "speaker": "SYSTEM",
                    "utterance": "多虧有您的配合，訊息已成功傳送"
               },
               {
                    "frames": [
                         {
                              "actions": [
                                   {
                                        "act": "INFORM_INTENT",
                                        "canonical_values": [
                                             "AddEvent"
                                        ],
                                        "slot": "intent",
                                        "values": [
                                             "AddEvent"
                                        ]
                                   }
                              ],
                              "service": "Calendar_1",
                              "slots": [],
                              "state": {
                                   "active_intent": "AddEvent",
                                   "requested_slots": [],
                                   "slot_values": {}
                              }
                         }
                    ],
                    "speaker": "USER",
                    "utterance": "我想要添加一個活動，可以請你幫忙嗎？"
               },
               {
                    "frames": [
                         {
                              "actions": [
                                   {
                                        "act": "REQUEST",
                                        "canonical_values": [],
                                        "slot": "event_location",
                                        "values": []
                                   }
                              ],
                              "service": "Calendar_1",
                              "slots": [],
                              "service_results": []
                         }
                    ],
                    "speaker": "SYSTEM",
                    "utterance": "我想知道這個活動的地點"
               },
               {
                    "frames": [
                         {
                              "actions": [
                                   {
                                        "act": "INFORM",
                                        "canonical_values": [
                                             "新北市231新店區碧潭風景區"
                                        ],
                                        "slot": "event_location",
                                        "values": [
                                             "新北市231新店區碧潭風景區"
                                        ]
                                   }
                              ],
                              "service": "Calendar_1",
                              "slots": [
                                   {
                                        "exclusive_end": 17,
                                        "slot": "event_location",
                                        "start": 3
                                   }
                              ],
                              "state": {
                                   "active_intent": "AddEvent",
                                   "requested_slots": [],
                                   "slot_values": {
                                        "event_location": [
                                             "新北市231新店區碧潭風景區"
                                        ]
                                   }
                              }
                         }
                    ],
                    "speaker": "USER",
                    "utterance": "地點為新北市231新店區碧潭風景區"
               },
               {
                    "frames": [
                         {
                              "actions": [
                                   {
                                        "act": "REQUEST",
                                        "canonical_values": [],
                                        "slot": "event_name",
                                        "values": []
                                   }
                              ],
                              "service": "Calendar_1",
                              "slots": [],
                              "service_results": []
                         }
                    ],
                    "speaker": "SYSTEM",
                    "utterance": "那這個活動叫甚麼呢？"
               },
               {
                    "frames": [
                         {
                              "actions": [
                                   {
                                        "act": "INFORM",
                                        "canonical_values": [
                                             "碧潭水舞"
                                        ],
                                        "slot": "event_name",
                                        "values": [
                                             "碧潭水舞"
                                        ]
                                   }
                              ],
                              "service": "Calendar_1",
                              "slots": [
                                   {
                                        "exclusive_end": 9,
                                        "slot": "event_name",
                                        "start": 5
                                   }
                              ],
                              "state": {
                                   "active_intent": "AddEvent",
                                   "requested_slots": [],
                                   "slot_values": {
                                        "event_location": [
                                             "新北市231新店區碧潭風景區"
                                        ],
                                        "event_name": [
                                             "碧潭水舞"
                                        ]
                                   }
                              }
                         }
                    ],
                    "speaker": "USER",
                    "utterance": "活動名稱叫碧潭水舞"
               },
               {
                    "frames": [
                         {
                              "actions": [
                                   {
                                        "act": "REQUEST",
                                        "canonical_values": [],
                                        "slot": "event_date",
                                        "values": []
                                   }
                              ],
                              "service": "Calendar_1",
                              "slots": [],
                              "service_results": []
                         }
                    ],
                    "speaker": "SYSTEM",
                    "utterance": "這個活動辦在幾月幾號呢？"
               },
               {
                    "frames": [
                         {
                              "actions": [
                                   {
                                        "act": "INFORM",
                                        "canonical_values": [
                                             "2022/4/23"
                                        ],
                                        "slot": "event_date",
                                        "values": [
                                             "2022年4月23號"
                                        ]
                                   }
                              ],
                              "service": "Calendar_1",
                              "slots": [
                                   {
                                        "exclusive_end": 13,
                                        "slot": "event_date",
                                        "start": 3
                                   }
                              ],
                              "state": {
                                   "active_intent": "AddEvent",
                                   "requested_slots": [],
                                   "slot_values": {
                                        "event_location": [
                                             "新北市231新店區碧潭風景區"
                                        ],
                                        "event_name": [
                                             "碧潭水舞"
                                        ],
                                        "event_date": [
                                             "2022年4月23號"
                                        ]
                                   }
                              }
                         }
                    ],
                    "speaker": "USER",
                    "utterance": "活動在2022年4月23號"
               },
               {
                    "frames": [
                         {
                              "actions": [
                                   {
                                        "act": "REQUEST",
                                        "canonical_values": [],
                                        "slot": "event_time",
                                        "values": []
                                   }
                              ],
                              "service": "Calendar_1",
                              "slots": [],
                              "service_results": []
                         }
                    ],
                    "speaker": "SYSTEM",
                    "utterance": "我想知道活動在當天何時開始"
               },
               {
                    "frames": [
                         {
                              "actions": [
                                   {
                                        "act": "INFORM",
                                        "canonical_values": [
                                             "09:18"
                                        ],
                                        "slot": "event_time",
                                        "values": [
                                             "9時18分"
                                        ]
                                   }
                              ],
                              "service": "Calendar_1",
                              "slots": [
                                   {
                                        "exclusive_end": 10,
                                        "slot": "event_time",
                                        "start": 5
                                   }
                              ],
                              "state": {
                                   "active_intent": "AddEvent",
                                   "requested_slots": [],
                                   "slot_values": {
                                        "event_location": [
                                             "新北市231新店區碧潭風景區"
                                        ],
                                        "event_name": [
                                             "碧潭水舞"
                                        ],
                                        "event_date": [
                                             "2022年4月23號"
                                        ],
                                        "event_time": [
                                             "9時18分"
                                        ]
                                   }
                              }
                         }
                    ],
                    "speaker": "USER",
                    "utterance": "活動時間為9時18分"
               },
               {
                    "frames": [
                         {
                              "actions": [
                                   {
                                        "act": "CONFIRM",
                                        "canonical_values": [
                                             "新北市231新店區碧潭風景區"
                                        ],
                                        "slot": "event_location",
                                        "values": [
                                             "新北市231新店區碧潭風景區"
                                        ]
                                   },
                                   {
                                        "act": "CONFIRM",
                                        "canonical_values": [
                                             "碧潭水舞"
                                        ],
                                        "slot": "event_name",
                                        "values": [
                                             "碧潭水舞"
                                        ]
                                   },
                                   {
                                        "act": "CONFIRM",
                                        "canonical_values": [
                                             "2022年4月23號"
                                        ],
                                        "slot": "event_date",
                                        "values": [
                                             "2022年4月23號"
                                        ]
                                   },
                                   {
                                        "act": "CONFIRM",
                                        "canonical_values": [
                                             "9時18分"
                                        ],
                                        "slot": "event_time",
                                        "values": [
                                             "9時18分"
                                        ]
                                   }
                              ],
                              "service": "Calendar_1",
                              "slots": [
                                   {
                                        "exclusive_end": 84,
                                        "slot": "event_location",
                                        "start": 70
                                   },
                                   {
                                        "exclusive_end": 11,
                                        "slot": "event_name",
                                        "start": 7
                                   },
                                   {
                                        "exclusive_end": 35,
                                        "slot": "event_date",
                                        "start": 25
                                   },
                                   {
                                        "exclusive_end": 56,
                                        "slot": "event_time",
                                        "start": 51
                                   }
                              ],
                              "service_results": []
                         }
                    ],
                    "speaker": "SYSTEM",
                    "utterance": "確認要建立名叫碧潭水舞的活動嗎？，確認要建立舉辦在2022年4月23號的活動嗎？，確認要建立舉辦在當天9時18分的活動嗎？，確認要建立舉辦在新北市231新店區碧潭風景區的活動嗎？"
               },
               {
                    "frames": [
                         {
                              "actions": [
                                   {
                                        "act": "AFFIRM",
                                        "canonical_values": [],
                                        "slot": "",
                                        "values": []
                                   }
                              ],
                              "service": "Calendar_1",
                              "slots": [],
                              "state": {
                                   "active_intent": "AddEvent",
                                   "requested_slots": [],
                                   "slot_values": {
                                        "event_location": [
                                             "新北市231新店區碧潭風景區"
                                        ],
                                        "event_name": [
                                             "碧潭水舞"
                                        ],
                                        "event_date": [
                                             "2022年4月23號"
                                        ],
                                        "event_time": [
                                             "9時18分"
                                        ]
                                   }
                              }
                         }
                    ],
                    "speaker": "USER",
                    "utterance": "好的，看起來沒甚麼問題"
               },
               {
                    "frames": [
                         {
                              "actions": [
                                   {
                                        "act": "NOTIFY_SUCCESS",
                                        "canonical_values": [],
                                        "slot": "",
                                        "values": []
                                   }
                              ],
                              "service": "Calendar_1",
                              "slots": [],
                              "service_call": {
                                   "method": "AddEvent",
                                   "parameters": {
                                        "event_location": "新北市231新店區碧潭風景區",
                                        "event_name": "碧潭水舞",
                                        "event_date": "2022年4月23號",
                                        "event_time": "9時18分"
                                   }
                              },
                              "service_results": []
                         }
                    ],
                    "speaker": "SYSTEM",
                    "utterance": "多虧有您的配合，活動已添加至行事曆"
               },
               {
                    "frames": [
                         {
                              "actions": [
                                   {
                                        "act": "SELECT",
                                        "canonical_values": [],
                                        "slot": "",
                                        "values": []
                                   }
                              ],
                              "service": "Calendar_1",
                              "slots": [],
                              "state": {
                                   "active_intent": "AddEvent",
                                   "requested_slots": [],
                                   "slot_values": {
                                        "event_location": [
                                             "新北市231新店區碧潭風景區"
                                        ],
                                        "event_name": [
                                             "碧潭水舞"
                                        ],
                                        "event_date": [
                                             "2022年4月23號"
                                        ],
                                        "event_time": [
                                             "9時18分"
                                        ]
                                   }
                              }
                         }
                    ],
                    "speaker": "USER",
                    "utterance": "我知道了"
               },
               {
                    "frames": [
                         {
                              "actions": [
                                   {
                                        "act": "GOODBYE",
                                        "canonical_values": [],
                                        "slot": "",
                                        "values": []
                                   }
                              ],
                              "service": "Calendar_1",
                              "slots": [],
                              "service_call": {
                                   "method": "AddEvent",
                                   "parameters": {
                                        "event_location": "新北市231新店區碧潭風景區",
                                        "event_name": "碧潭水舞",
                                        "event_date": "2022年4月23號",
                                        "event_time": "9時18分"
                                   }
                              },
                              "service_results": []
                         }
                    ],
                    "speaker": "SYSTEM",
                    "utterance": "嗯，再見"
               }
          ]
     }
]